aio_lambda_api/__init__.py
aio_lambda_api/_backends/__init__.py
aio_lambda_api/_backends/aws_lambda.py
aio_lambda_api/_core.py
aio_lambda_api/_requests.py
aio_lambda_api/_responses.py
aio_lambda_api/exceptions.py
aio_lambda_api/json.py
aio_lambda_api/py.typed
aio_lambda_api/settings.py
aio_lambda_api/status.py
aio_lambda_api-0.3.1.dist-info/LICENSE
aio_lambda_api-0.3.1.dist-info/WHEEL
aio_lambda_api-0.3.1.dist-info/METADATA
aio_lambda_api-0.3.1.dist-info/RECORD
