Metadata-Version: 2.1
Name: aio-lambda-api
Version: 0.3.1
Summary: Simple AsyncIO AWS lambda HTTP API
Home-page: https://github.com/JGoutin/aio_lambda_api
License: BSD-2-Clause
Keywords: aws,lambda,http,API,asyncio
Author: JGoutin
Requires-Python: >=3.8,<4.0
Classifier: Development Status :: 4 - Beta
Classifier: Framework :: AsyncIO
Classifier: Intended Audience :: Developers
Classifier: License :: OSI Approved :: BSD License
Classifier: Programming Language :: Python :: 3
Classifier: Programming Language :: Python :: 3.8
Classifier: Programming Language :: Python :: 3.9
Classifier: Programming Language :: Python :: 3.10
Classifier: Programming Language :: Python :: 3.11
Classifier: Topic :: Internet :: WWW/HTTP :: HTTP Servers
Classifier: Typing :: Typed
Provides-Extra: all
Provides-Extra: aws
Provides-Extra: speedups
Provides-Extra: validation
Requires-Dist: aioboto3 ; extra == "all" or extra == "aws"
Requires-Dist: aiohttp[speedups] (>3.8) ; extra == "all" or extra == "speedups"
Requires-Dist: jhalog
Requires-Dist: orjson ; extra == "all" or extra == "speedups"
Requires-Dist: pydantic ; extra == "all" or extra == "validation"
Requires-Dist: uvloop ; extra == "all" or extra == "speedups"
Project-URL: Repository, https://github.com/JGoutin/aio_lambda_api
